lichvPy3mysql
